[
    {
        "id": 1,
        "title": "User 01 Contribution For his Mother",
        "description": "Description for this title is here.",
        "Contributors": [
            {
                "id": 1,
                "name": "Brayan Mlawa",
                "amount": 70000,
                "avatar": "/avatars/shadcn.jpg"
            },
            {
                "id": 2,
                "name": "Rashid Salum",
                "amount": 50000,
                "avatar": "/avatars/shadcn.jpg"
            },
            {
                "id": 3,
                "name": "Salma Juma",
                "amount": 12000,
                "avatar": "/avatars/shadcn.jpg"
            },
            {
                "id": 4,
                "name": "Nyoi Mtole",
                "amount": 3000,
                "avatar": "/avatars/shadcn.jpg"
            },
            {
                "id": 5,
                "name": "Punda John",
                "amount": 30000,
                "avatar": "/avatars/shadcn.jpg"
            },
            {
                "id": 6,
                "name": "Cleyton Masantula",
                "amount": 5000,
                "avatar": "/avatars/shadcn.jpg"
            },
            {
                "id": 7,
                "name": "John Doe",
                "amount": 10000,
                "avatar": "/avatars/shadcn.jpg"
            }
        ]
    },
    {
        "id": 2,
        "title": "User 02 Contribution For his Father",
        "description": "Description for this title is here.",
        "Contributors": [
            {
                "id": 1,
                "name": "Brayan Mlawa",
                "amount": 70000,
                "avatar": "/avatars/shadcn.jpg"
            },
            {
                "id": 2,
                "name": "Rashid Salum",
                "amount": 50000,
                "avatar": "/avatars/shadcn.jpg"
            },
            {
                "id": 3,
                "name": "Salma Juma",
                "amount": 12000,
                "avatar": "/avatars/shadcn.jpg"
            },
            {
                "id": 4,
                "name": "Nyoi Mtole",
                "amount": 3000,
                "avatar": "/avatars/shadcn.jpg"
            },
            {
                "id": 5,
                "name": "Punda John",
                "amount": 30000,
                "avatar": "/avatars/shadcn.jpg"
            },
            {
                "id": 6,
                "name": "Cleyton Masantula",
                "amount": 5000,
                "avatar": "/avatars/shadcn.jpg"
            },
            {
                "id": 7,
                "name": "John Doe",
                "amount": 10000,
                "avatar": "/avatars/shadcn.jpg"
            }
        ]
    },
    {
        "id": 3,
        "title": "User 03 Contribution For his Mother",
        "description": "Description for this title is here.",
        "Contributors": [
            {
                "id": 1,
                "name": "Brayan Mlawa",
                "amount": 70000,
                "avatar": "/avatars/shadcn.jpg"
            },
            {
                "id": 2,
                "name": "Rashid Salum",
                "amount": 50000,
                "avatar": "/avatars/shadcn.jpg"
            },
            {
                "id": 3,
                "name": "Salma Juma",
                "amount": 12000,
                "avatar": "/avatars/shadcn.jpg"
            },
            {
                "id": 4,
                "name": "Nyoi Mtole",
                "amount": 3000,
                "avatar": "/avatars/shadcn.jpg"
            },
            {
                "id": 5,
                "name": "Punda John",
                "amount": 30000,
                "avatar": "/avatars/shadcn.jpg"
            },
            {
                "id": 6,
                "name": "Cleyton Masantula",
                "amount": 5000,
                "avatar": "/avatars/shadcn.jpg"
            },
            {
                "id": 7,
                "name": "John Doe",
                "amount": 10000,
                "avatar": "/avatars/shadcn.jpg"
            }
        ]
    },
    {
        "id": 4,
        "title": "User 04 Contribution For his Uncle",
        "description": "Description for this title is here.",
        "Contributors": [
            {
                "id": 1,
                "name": "Brayan Mlawa",
                "amount": 70000,
                "avatar": "/avatars/shadcn.jpg"
            },
            {
                "id": 2,
                "name": "Rashid Salum",
                "amount": 50000,
                "avatar": "/avatars/shadcn.jpg"
            },
            {
                "id": 3,
                "name": "Salma Juma",
                "amount": 12000,
                "avatar": "/avatars/shadcn.jpg"
            },
            {
                "id": 4,
                "name": "Nyoi Mtole",
                "amount": 3000,
                "avatar": "/avatars/shadcn.jpg"
            },
            {
                "id": 5,
                "name": "Punda John",
                "amount": 30000,
                "avatar": "/avatars/shadcn.jpg"
            },
            {
                "id": 6,
                "name": "Cleyton Masantula",
                "amount": 5000,
                "avatar": "/avatars/shadcn.jpg"
            },
            {
                "id": 7,
                "name": "John Doe",
                "amount": 10000,
                "avatar": "/avatars/shadcn.jpg"
            }
        ]
    },
    {
        "id": 5,
        "title": "User 01 Contribution For his Friend",
        "description": "Description for this title is here.",
        "Contributors": [
            {
                "id": 1,
                "name": "Brayan Mlawa",
                "amount": 70000,
                "avatar": "/avatars/shadcn.jpg"
            },
            {
                "id": 2,
                "name": "Rashid Salum",
                "amount": 50000,
                "avatar": "/avatars/shadcn.jpg"
            },
            {
                "id": 3,
                "name": "Salma Juma",
                "amount": 12000,
                "avatar": "/avatars/shadcn.jpg"
            },
            {
                "id": 4,
                "name": "Nyoi Mtole",
                "amount": 3000,
                "avatar": "/avatars/shadcn.jpg"
            },
            {
                "id": 5,
                "name": "Punda John",
                "amount": 30000,
                "avatar": "/avatars/shadcn.jpg"
            },
            {
                "id": 6,
                "name": "Cleyton Masantula",
                "amount": 5000,
                "avatar": "/avatars/shadcn.jpg"
            },
            {
                "id": 7,
                "name": "John Doe",
                "amount": 10000,
                "avatar": "/avatars/shadcn.jpg"
            }
        ]
    },
    {
        "id": 6,
        "title": "User 01 Contribution For his Mother",
        "description": "Description for this title is here.",
        "Contributors": [
            {
                "id": 1,
                "name": "Brayan Mlawa",
                "amount": 70000,
                "avatar": "/avatars/shadcn.jpg"
            },
            {
                "id": 2,
                "name": "Rashid Salum",
                "amount": 50000,
                "avatar": "/avatars/shadcn.jpg"
            },
            {
                "id": 3,
                "name": "Salma Juma",
                "amount": 12000,
                "avatar": "/avatars/shadcn.jpg"
            },
            {
                "id": 4,
                "name": "Nyoi Mtole",
                "amount": 3000,
                "avatar": "/avatars/shadcn.jpg"
            },
            {
                "id": 5,
                "name": "Punda John",
                "amount": 30000,
                "avatar": "/avatars/shadcn.jpg"
            },
            {
                "id": 6,
                "name": "Cleyton Masantula",
                "amount": 5000,
                "avatar": "/avatars/shadcn.jpg"
            },
            {
                "id": 7,
                "name": "John Doe",
                "amount": 10000,
                "avatar": "/avatars/shadcn.jpg"
            }
        ]
    },
    {
        "id": 7,
        "title": "User 01 Contribution For his Mother",
        "description": "Description for this title is here.",
        "Contributors": [
            {
                "id": 1,
                "name": "Brayan Mlawa",
                "amount": 70000,
                "avatar": "/avatars/shadcn.jpg"
            },
            {
                "id": 2,
                "name": "Rashid Salum",
                "amount": 50000,
                "avatar": "/avatars/shadcn.jpg"
            },
            {
                "id": 3,
                "name": "Salma Juma",
                "amount": 12000,
                "avatar": "/avatars/shadcn.jpg"
            },
            {
                "id": 4,
                "name": "Nyoi Mtole",
                "amount": 3000,
                "avatar": "/avatars/shadcn.jpg"
            },
            {
                "id": 5,
                "name": "Punda John",
                "amount": 30000,
                "avatar": "/avatars/shadcn.jpg"
            },
            {
                "id": 6,
                "name": "Cleyton Masantula",
                "amount": 5000,
                "avatar": "/avatars/shadcn.jpg"
            },
            {
                "id": 7,
                "name": "John Doe",
                "amount": 10000,
                "avatar": "/avatars/shadcn.jpg"
            }
        ]
    },
    {
        "id": 8,
        "title": "User 01 Contribution For his Mother",
        "description": "Description for this title is here.",
        "Contributors": [
            {
                "id": 1,
                "name": "Brayan Mlawa",
                "amount": 70000,
                "avatar": "/avatars/shadcn.jpg"
            },
            {
                "id": 2,
                "name": "Rashid Salum",
                "amount": 50000,
                "avatar": "/avatars/shadcn.jpg"
            },
            {
                "id": 3,
                "name": "Salma Juma",
                "amount": 12000,
                "avatar": "/avatars/shadcn.jpg"
            },
            {
                "id": 4,
                "name": "Nyoi Mtole",
                "amount": 3000,
                "avatar": "/avatars/shadcn.jpg"
            },
            {
                "id": 5,
                "name": "Punda John",
                "amount": 30000,
                "avatar": "/avatars/shadcn.jpg"
            },
            {
                "id": 6,
                "name": "Cleyton Masantula",
                "amount": 5000,
                "avatar": "/avatars/shadcn.jpg"
            },
            {
                "id": 7,
                "name": "John Doe",
                "amount": 10000,
                "avatar": "/avatars/shadcn.jpg"
            }
        ]
    },
    {
        "id": 9,
        "title": "User 01 Contribution For his Mother",
        "description": "Description for this title is here.",
        "Contributors": [
            {
                "id": 1,
                "name": "Brayan Mlawa",
                "amount": 70000,
                "avatar": "/avatars/shadcn.jpg"
            },
            {
                "id": 2,
                "name": "Rashid Salum",
                "amount": 50000,
                "avatar": "/avatars/shadcn.jpg"
            },
            {
                "id": 3,
                "name": "Salma Juma",
                "amount": 12000,
                "avatar": "/avatars/shadcn.jpg"
            },
            {
                "id": 4,
                "name": "Nyoi Mtole",
                "amount": 3000,
                "avatar": "/avatars/shadcn.jpg"
            },
            {
                "id": 5,
                "name": "Punda John",
                "amount": 30000,
                "avatar": "/avatars/shadcn.jpg"
            },
            {
                "id": 6,
                "name": "Cleyton Masantula",
                "amount": 5000,
                "avatar": "/avatars/shadcn.jpg"
            },
            {
                "id": 7,
                "name": "John Doe",
                "amount": 10000,
                "avatar": "/avatars/shadcn.jpg"
            }
        ]
    },
    {
        "id": 10,
        "title": "User 01 Contribution For his Mother",
        "description": "Description for this title is here.",
        "Contributors": [
            {
                "id": 1,
                "name": "Brayan Mlawa",
                "amount": 70000,
                "avatar": "/avatars/shadcn.jpg"
            },
            {
                "id": 2,
                "name": "Rashid Salum",
                "amount": 50000,
                "avatar": "/avatars/shadcn.jpg"
            },
            {
                "id": 3,
                "name": "Salma Juma",
                "amount": 12000,
                "avatar": "/avatars/shadcn.jpg"
            },
            {
                "id": 4,
                "name": "Nyoi Mtole",
                "amount": 3000,
                "avatar": "/avatars/shadcn.jpg"
            },
            {
                "id": 5,
                "name": "Punda John",
                "amount": 30000,
                "avatar": "/avatars/shadcn.jpg"
            },
            {
                "id": 6,
                "name": "Cleyton Masantula",
                "amount": 5000,
                "avatar": "/avatars/shadcn.jpg"
            },
            {
                "id": 7,
                "name": "John Doe",
                "amount": 10000,
                "avatar": "/avatars/shadcn.jpg"
            }
        ]
    },
    {
        "id": 11,
        "title": "User 01 Contribution For his Mother",
        "description": "Description for this title is here.",
        "Contributors": [
            {
                "id": 1,
                "name": "Brayan Mlawa",
                "amount": 70000,
                "avatar": "/avatars/shadcn.jpg"
            },
            {
                "id": 2,
                "name": "Rashid Salum",
                "amount": 50000,
                "avatar": "/avatars/shadcn.jpg"
            },
            {
                "id": 3,
                "name": "Salma Juma",
                "amount": 12000,
                "avatar": "/avatars/shadcn.jpg"
            },
            {
                "id": 4,
                "name": "Nyoi Mtole",
                "amount": 3000,
                "avatar": "/avatars/shadcn.jpg"
            },
            {
                "id": 5,
                "name": "Punda John",
                "amount": 30000,
                "avatar": "/avatars/shadcn.jpg"
            },
            {
                "id": 6,
                "name": "Cleyton Masantula",
                "amount": 5000,
                "avatar": "/avatars/shadcn.jpg"
            },
            {
                "id": 7,
                "name": "John Doe",
                "amount": 10000,
                "avatar": "/avatars/shadcn.jpg"
            }
        ]
    },
    {
        "id": 12,
        "title": "User 01 Contribution For his Mother",
        "description": "Description for this title is here.",
        "Contributors": [
            {
                "id": 1,
                "name": "Brayan Mlawa",
                "amount": 70000,
                "avatar": "/avatars/shadcn.jpg"
            },
            {
                "id": 2,
                "name": "Rashid Salum",
                "amount": 50000,
                "avatar": "/avatars/shadcn.jpg"
            },
            {
                "id": 3,
                "name": "Salma Juma",
                "amount": 12000,
                "avatar": "/avatars/shadcn.jpg"
            },
            {
                "id": 4,
                "name": "Nyoi Mtole",
                "amount": 3000,
                "avatar": "/avatars/shadcn.jpg"
            },
            {
                "id": 5,
                "name": "Punda John",
                "amount": 30000,
                "avatar": "/avatars/shadcn.jpg"
            },
            {
                "id": 6,
                "name": "Cleyton Masantula",
                "amount": 5000,
                "avatar": "/avatars/shadcn.jpg"
            },
            {
                "id": 7,
                "name": "John Doe",
                "amount": 10000,
                "avatar": "/avatars/shadcn.jpg"
            }
        ]
    },
    {
        "id": 13,
        "title": "User 01 Contribution For his Mother",
        "description": "Description for this title is here.",
        "Contributors": [
            {
                "id": 1,
                "name": "Brayan Mlawa",
                "amount": 70000,
                "avatar": "/avatars/shadcn.jpg"
            },
            {
                "id": 2,
                "name": "Rashid Salum",
                "amount": 50000,
                "avatar": "/avatars/shadcn.jpg"
            },
            {
                "id": 3,
                "name": "Salma Juma",
                "amount": 12000,
                "avatar": "/avatars/shadcn.jpg"
            },
            {
                "id": 4,
                "name": "Nyoi Mtole",
                "amount": 3000,
                "avatar": "/avatars/shadcn.jpg"
            },
            {
                "id": 5,
                "name": "Punda John",
                "amount": 30000,
                "avatar": "/avatars/shadcn.jpg"
            },
            {
                "id": 6,
                "name": "Cleyton Masantula",
                "amount": 5000,
                "avatar": "/avatars/shadcn.jpg"
            },
            {
                "id": 7,
                "name": "John Doe",
                "amount": 10000,
                "avatar": "/avatars/shadcn.jpg"
            }
        ]
    },
    {
        "id": 14,
        "title": "User 01 Contribution For his Mother",
        "description": "Description for this title is here.",
        "Contributors": [
            {
                "id": 1,
                "name": "Brayan Mlawa",
                "amount": 70000,
                "avatar": "/avatars/shadcn.jpg"
            },
            {
                "id": 2,
                "name": "Rashid Salum",
                "amount": 50000,
                "avatar": "/avatars/shadcn.jpg"
            },
            {
                "id": 3,
                "name": "Salma Juma",
                "amount": 12000,
                "avatar": "/avatars/shadcn.jpg"
            },
            {
                "id": 4,
                "name": "Nyoi Mtole",
                "amount": 3000,
                "avatar": "/avatars/shadcn.jpg"
            },
            {
                "id": 5,
                "name": "Punda John",
                "amount": 30000,
                "avatar": "/avatars/shadcn.jpg"
            },
            {
                "id": 6,
                "name": "Cleyton Masantula",
                "amount": 5000,
                "avatar": "/avatars/shadcn.jpg"
            },
            {
                "id": 7,
                "name": "John Doe",
                "amount": 10000,
                "avatar": "/avatars/shadcn.jpg"
            }
        ]
    },
    {
        "id": 15,
        "title": "User 01 Contribution For his Mother",
        "description": "Description for this title is here.",
        "Contributors": [
            {
                "id": 1,
                "name": "Brayan Mlawa",
                "amount": 70000,
                "avatar": "/avatars/shadcn.jpg"
            },
            {
                "id": 2,
                "name": "Rashid Salum",
                "amount": 50000,
                "avatar": "/avatars/shadcn.jpg"
            },
            {
                "id": 3,
                "name": "Salma Juma",
                "amount": 12000,
                "avatar": "/avatars/shadcn.jpg"
            },
            {
                "id": 4,
                "name": "Nyoi Mtole",
                "amount": 3000,
                "avatar": "/avatars/shadcn.jpg"
            },
            {
                "id": 5,
                "name": "Punda John",
                "amount": 30000,
                "avatar": "/avatars/shadcn.jpg"
            },
            {
                "id": 6,
                "name": "Cleyton Masantula",
                "amount": 5000,
                "avatar": "/avatars/shadcn.jpg"
            },
            {
                "id": 7,
                "name": "John Doe",
                "amount": 10000,
                "avatar": "/avatars/shadcn.jpg"
            }
        ]
    }

]